<annotation>
	<folder>Folder 01_jpg</folder>
	<filename>002_00022112.jpg</filename>
	<path>D:\data\wheat_spider\Folder 01_jpg\002_00022112.jpg</path>
	<source>
		<database>Unknown</database>
	</source>
	<size>
		<width>360</width>
		<height>270</height>
		<depth>3</depth>
	</size>
	<segmented>0</segmented>
	<object>
		<name>11111</name>
		<pose>Unspecified</pose>
		<truncated>0</truncated>
		<difficult>0</difficult>
		<bndbox>
			<xmin>104</xmin>
			<ymin>121</ymin>
			<xmax>112</xmax>
			<ymax>128</ymax>
		</bndbox>
	</object>
	<object>
		<name>11111</name>
		<pose>Unspecified</pose>
		<truncated>0</truncated>
		<difficult>0</difficult>
		<bndbox>
			<xmin>158</xmin>
			<ymin>186</ymin>
			<xmax>164</xmax>
			<ymax>192</ymax>
		</bndbox>
	</object>
	<object>
		<name>11111</name>
		<pose>Unspecified</pose>
		<truncated>0</truncated>
		<difficult>0</difficult>
		<bndbox>
			<xmin>222</xmin>
			<ymin>210</ymin>
			<xmax>228</xmax>
			<ymax>216</ymax>
		</bndbox>
	</object>
	<object>
		<name>11111</name>
		<pose>Unspecified</pose>
		<truncated>0</truncated>
		<difficult>0</difficult>
		<bndbox>
			<xmin>335</xmin>
			<ymin>215</ymin>
			<xmax>346</xmax>
			<ymax>224</ymax>
		</bndbox>
	</object>
	<object>
		<name>11111</name>
		<pose>Unspecified</pose>
		<truncated>0</truncated>
		<difficult>0</difficult>
		<bndbox>
			<xmin>90</xmin>
			<ymin>185</ymin>
			<xmax>94</xmax>
			<ymax>190</ymax>
		</bndbox>
	</object>
</annotation>
