<annotation verified="no">
  <folder>feishi</folder>
  <filename>1109</filename>
  <path>D:\feishi\1109.JPG</path>
  <source>
    <database>Unknown</database>
  </source>
  <size>
    <width>1440</width>
    <height>1080</height>
    <depth>3</depth>
  </size>
  <segmented>0</segmented>
  <object>
    <name>1</name>
    <pose>Unspecified</pose>
    <truncated>0</truncated>
    <difficult>0</difficult>
    <bndbox>
      <xmin>732</xmin>
      <ymin>530</ymin>
      <xmax>780</xmax>
      <ymax>605</ymax>
    </bndbox>
  </object>
  <object>
    <name>1</name>
    <pose>Unspecified</pose>
    <truncated>0</truncated>
    <difficult>0</difficult>
    <bndbox>
      <xmin>1102</xmin>
      <ymin>621</ymin>
      <xmax>1152</xmax>
      <ymax>689</ymax>
    </bndbox>
  </object>
  <object>
    <name>1</name>
    <pose>Unspecified</pose>
    <truncated>0</truncated>
    <difficult>0</difficult>
    <bndbox>
      <xmin>734</xmin>
      <ymin>604</ymin>
      <xmax>777</xmax>
      <ymax>662</ymax>
    </bndbox>
  </object>
  <object>
    <name>1</name>
    <pose>Unspecified</pose>
    <truncated>0</truncated>
    <difficult>0</difficult>
    <bndbox>
      <xmin>467</xmin>
      <ymin>322</ymin>
      <xmax>520</xmax>
      <ymax>389</ymax>
    </bndbox>
  </object>
  <object>
    <name>1</name>
    <pose>Unspecified</pose>
    <truncated>0</truncated>
    <difficult>0</difficult>
    <bndbox>
      <xmin>845</xmin>
      <ymin>1003</ymin>
      <xmax>896</xmax>
      <ymax>1075</ymax>
    </bndbox>
  </object>
  <object>
    <name>1</name>
    <pose>Unspecified</pose>
    <truncated>0</truncated>
    <difficult>0</difficult>
    <bndbox>
      <xmin>305</xmin>
      <ymin>51</ymin>
      <xmax>353</xmax>
      <ymax>111</ymax>
    </bndbox>
  </object>
  <object>
    <name>1</name>
    <pose>Unspecified</pose>
    <truncated>0</truncated>
    <difficult>0</difficult>
    <bndbox>
      <xmin>700</xmin>
      <ymin>457</ymin>
      <xmax>743</xmax>
      <ymax>515</ymax>
    </bndbox>
  </object>
  <object>
    <name>1</name>
    <pose>Unspecified</pose>
    <truncated>0</truncated>
    <difficult>0</difficult>
    <bndbox>
      <xmin>1409</xmin>
      <ymin>876</ymin>
      <xmax>1438</xmax>
      <ymax>958</ymax>
    </bndbox>
  </object>
  <object>
    <name>1</name>
    <pose>Unspecified</pose>
    <truncated>0</truncated>
    <difficult>0</difficult>
    <bndbox>
      <xmin>560</xmin>
      <ymin>435</ymin>
      <xmax>603</xmax>
      <ymax>490</ymax>
    </bndbox>
  </object>
  <object>
    <name>1</name>
    <pose>Unspecified</pose>
    <truncated>0</truncated>
    <difficult>0</difficult>
    <bndbox>
      <xmin>185</xmin>
      <ymin>371</ymin>
      <xmax>256</xmax>
      <ymax>481</ymax>
    </bndbox>
  </object>
  <object>
    <name>1</name>
    <pose>Unspecified</pose>
    <truncated>0</truncated>
    <difficult>0</difficult>
    <bndbox>
      <xmin>786</xmin>
      <ymin>532</ymin>
      <xmax>825</xmax>
      <ymax>585</ymax>
    </bndbox>
  </object>
  <object>
    <name>1</name>
    <pose>Unspecified</pose>
    <truncated>0</truncated>
    <difficult>0</difficult>
    <bndbox>
      <xmin>531</xmin>
      <ymin>522</ymin>
      <xmax>596</xmax>
      <ymax>599</ymax>
    </bndbox>
  </object>
  <object>
    <name>1</name>
    <pose>Unspecified</pose>
    <truncated>0</truncated>
    <difficult>0</difficult>
    <bndbox>
      <xmin>1080</xmin>
      <ymin>512</ymin>
      <xmax>1143</xmax>
      <ymax>592</ymax>
    </bndbox>
  </object>
  <object>
    <name>1</name>
    <pose>Unspecified</pose>
    <truncated>0</truncated>
    <difficult>0</difficult>
    <bndbox>
      <xmin>462</xmin>
      <ymin>383</ymin>
      <xmax>511</xmax>
      <ymax>442</ymax>
    </bndbox>
  </object>
  <object>
    <name>1</name>
    <pose>Unspecified</pose>
    <truncated>0</truncated>
    <difficult>0</difficult>
    <bndbox>
      <xmin>356</xmin>
      <ymin>97</ymin>
      <xmax>406</xmax>
      <ymax>202</ymax>
    </bndbox>
  </object>
</annotation>
