<annotation verified="no">
  <folder>daofeishi</folder>
  <filename>1472</filename>
  <path>C:\Users\xiekezi\Desktop\labelimg_windows_v1.3.2\windows_v1.3.2\daofeishi\1472.JPG</path>
  <source>
    <database>Unknown</database>
  </source>
  <size>
    <width>1440</width>
    <height>1080</height>
    <depth>3</depth>
  </size>
  <segmented>0</segmented>
  <object>
    <name>1</name>
    <pose>Unspecified</pose>
    <truncated>0</truncated>
    <difficult>0</difficult>
    <bndbox>
      <xmin>583</xmin>
      <ymin>156</ymin>
      <xmax>626</xmax>
      <ymax>214</ymax>
    </bndbox>
  </object>
  <object>
    <name>1</name>
    <pose>Unspecified</pose>
    <truncated>0</truncated>
    <difficult>0</difficult>
    <bndbox>
      <xmin>441</xmin>
      <ymin>945</ymin>
      <xmax>485</xmax>
      <ymax>1006</ymax>
    </bndbox>
  </object>
  <object>
    <name>1</name>
    <pose>Unspecified</pose>
    <truncated>0</truncated>
    <difficult>0</difficult>
    <bndbox>
      <xmin>495</xmin>
      <ymin>822</ymin>
      <xmax>531</xmax>
      <ymax>872</ymax>
    </bndbox>
  </object>
  <object>
    <name>1</name>
    <pose>Unspecified</pose>
    <truncated>0</truncated>
    <difficult>0</difficult>
    <bndbox>
      <xmin>417</xmin>
      <ymin>22</ymin>
      <xmax>445</xmax>
      <ymax>56</ymax>
    </bndbox>
  </object>
  <object>
    <name>1</name>
    <pose>Unspecified</pose>
    <truncated>0</truncated>
    <difficult>0</difficult>
    <bndbox>
      <xmin>692</xmin>
      <ymin>64</ymin>
      <xmax>734</xmax>
      <ymax>112</ymax>
    </bndbox>
  </object>
  <object>
    <name>1</name>
    <pose>Unspecified</pose>
    <truncated>0</truncated>
    <difficult>0</difficult>
    <bndbox>
      <xmin>392</xmin>
      <ymin>244</ymin>
      <xmax>429</xmax>
      <ymax>289</ymax>
    </bndbox>
  </object>
  <object>
    <name>1</name>
    <pose>Unspecified</pose>
    <truncated>0</truncated>
    <difficult>0</difficult>
    <bndbox>
      <xmin>589</xmin>
      <ymin>245</ymin>
      <xmax>631</xmax>
      <ymax>319</ymax>
    </bndbox>
  </object>
  <object>
    <name>1</name>
    <pose>Unspecified</pose>
    <truncated>1</truncated>
    <difficult>0</difficult>
    <bndbox>
      <xmin>563</xmin>
      <ymin>1</ymin>
      <xmax>599</xmax>
      <ymax>38</ymax>
    </bndbox>
  </object>
  <object>
    <name>1</name>
    <pose>Unspecified</pose>
    <truncated>0</truncated>
    <difficult>0</difficult>
    <bndbox>
      <xmin>576</xmin>
      <ymin>419</ymin>
      <xmax>617</xmax>
      <ymax>464</ymax>
    </bndbox>
  </object>
  <object>
    <name>1</name>
    <pose>Unspecified</pose>
    <truncated>0</truncated>
    <difficult>0</difficult>
    <bndbox>
      <xmin>474</xmin>
      <ymin>671</ymin>
      <xmax>506</xmax>
      <ymax>710</ymax>
    </bndbox>
  </object>
  <object>
    <name>1</name>
    <pose>Unspecified</pose>
    <truncated>0</truncated>
    <difficult>0</difficult>
    <bndbox>
      <xmin>824</xmin>
      <ymin>950</ymin>
      <xmax>867</xmax>
      <ymax>1022</ymax>
    </bndbox>
  </object>
  <object>
    <name>1</name>
    <pose>Unspecified</pose>
    <truncated>0</truncated>
    <difficult>0</difficult>
    <bndbox>
      <xmin>10</xmin>
      <ymin>122</ymin>
      <xmax>42</xmax>
      <ymax>156</ymax>
    </bndbox>
  </object>
</annotation>
