<annotation verified="no">
  <folder>feishi</folder>
  <filename>1730</filename>
  <path>D:\feishi\1730.JPG</path>
  <source>
    <database>Unknown</database>
  </source>
  <size>
    <width>1440</width>
    <height>1080</height>
    <depth>3</depth>
  </size>
  <segmented>0</segmented>
  <object>
    <name>1</name>
    <pose>Unspecified</pose>
    <truncated>0</truncated>
    <difficult>0</difficult>
    <bndbox>
      <xmin>1182</xmin>
      <ymin>342</ymin>
      <xmax>1231</xmax>
      <ymax>407</ymax>
    </bndbox>
  </object>
  <object>
    <name>1</name>
    <pose>Unspecified</pose>
    <truncated>0</truncated>
    <difficult>0</difficult>
    <bndbox>
      <xmin>959</xmin>
      <ymin>637</ymin>
      <xmax>1001</xmax>
      <ymax>695</ymax>
    </bndbox>
  </object>
  <object>
    <name>1</name>
    <pose>Unspecified</pose>
    <truncated>0</truncated>
    <difficult>0</difficult>
    <bndbox>
      <xmin>986</xmin>
      <ymin>721</ymin>
      <xmax>1024</xmax>
      <ymax>776</ymax>
    </bndbox>
  </object>
  <object>
    <name>1</name>
    <pose>Unspecified</pose>
    <truncated>0</truncated>
    <difficult>0</difficult>
    <bndbox>
      <xmin>1013</xmin>
      <ymin>872</ymin>
      <xmax>1055</xmax>
      <ymax>933</ymax>
    </bndbox>
  </object>
  <object>
    <name>1</name>
    <pose>Unspecified</pose>
    <truncated>0</truncated>
    <difficult>0</difficult>
    <bndbox>
      <xmin>1156</xmin>
      <ymin>706</ymin>
      <xmax>1193</xmax>
      <ymax>759</ymax>
    </bndbox>
  </object>
  <object>
    <name>1</name>
    <pose>Unspecified</pose>
    <truncated>0</truncated>
    <difficult>0</difficult>
    <bndbox>
      <xmin>1207</xmin>
      <ymin>676</ymin>
      <xmax>1234</xmax>
      <ymax>724</ymax>
    </bndbox>
  </object>
  <object>
    <name>1</name>
    <pose>Unspecified</pose>
    <truncated>0</truncated>
    <difficult>0</difficult>
    <bndbox>
      <xmin>1183</xmin>
      <ymin>873</ymin>
      <xmax>1213</xmax>
      <ymax>921</ymax>
    </bndbox>
  </object>
  <object>
    <name>1</name>
    <pose>Unspecified</pose>
    <truncated>0</truncated>
    <difficult>0</difficult>
    <bndbox>
      <xmin>1131</xmin>
      <ymin>766</ymin>
      <xmax>1169</xmax>
      <ymax>821</ymax>
    </bndbox>
  </object>
  <object>
    <name>1</name>
    <pose>Unspecified</pose>
    <truncated>0</truncated>
    <difficult>0</difficult>
    <bndbox>
      <xmin>1154</xmin>
      <ymin>827</ymin>
      <xmax>1186</xmax>
      <ymax>876</ymax>
    </bndbox>
  </object>
  <object>
    <name>1</name>
    <pose>Unspecified</pose>
    <truncated>0</truncated>
    <difficult>0</difficult>
    <bndbox>
      <xmin>882</xmin>
      <ymin>483</ymin>
      <xmax>914</xmax>
      <ymax>538</ymax>
    </bndbox>
  </object>
</annotation>
