<annotation verified="no">
  <folder>feishi</folder>
  <filename>1936</filename>
  <path>D:\feishi\1936.JPG</path>
  <source>
    <database>Unknown</database>
  </source>
  <size>
    <width>1440</width>
    <height>1080</height>
    <depth>3</depth>
  </size>
  <segmented>0</segmented>
  <object>
    <name>1</name>
    <pose>Unspecified</pose>
    <truncated>0</truncated>
    <difficult>0</difficult>
    <bndbox>
      <xmin>582</xmin>
      <ymin>278</ymin>
      <xmax>635</xmax>
      <ymax>358</ymax>
    </bndbox>
  </object>
  <object>
    <name>1</name>
    <pose>Unspecified</pose>
    <truncated>0</truncated>
    <difficult>0</difficult>
    <bndbox>
      <xmin>604</xmin>
      <ymin>724</ymin>
      <xmax>666</xmax>
      <ymax>790</ymax>
    </bndbox>
  </object>
</annotation>
