<annotation verified="no">
  <folder>feishi</folder>
  <filename>2006</filename>
  <path>D:\feishi\2006.JPG</path>
  <source>
    <database>Unknown</database>
  </source>
  <size>
    <width>1440</width>
    <height>1080</height>
    <depth>3</depth>
  </size>
  <segmented>0</segmented>
  <object>
    <name>1</name>
    <pose>Unspecified</pose>
    <truncated>0</truncated>
    <difficult>0</difficult>
    <bndbox>
      <xmin>213</xmin>
      <ymin>468</ymin>
      <xmax>268</xmax>
      <ymax>540</ymax>
    </bndbox>
  </object>
  <object>
    <name>1</name>
    <pose>Unspecified</pose>
    <truncated>0</truncated>
    <difficult>0</difficult>
    <bndbox>
      <xmin>194</xmin>
      <ymin>557</ymin>
      <xmax>238</xmax>
      <ymax>616</ymax>
    </bndbox>
  </object>
  <object>
    <name>1</name>
    <pose>Unspecified</pose>
    <truncated>0</truncated>
    <difficult>0</difficult>
    <bndbox>
      <xmin>504</xmin>
      <ymin>295</ymin>
      <xmax>549</xmax>
      <ymax>358</ymax>
    </bndbox>
  </object>
  <object>
    <name>1</name>
    <pose>Unspecified</pose>
    <truncated>0</truncated>
    <difficult>0</difficult>
    <bndbox>
      <xmin>456</xmin>
      <ymin>411</ymin>
      <xmax>497</xmax>
      <ymax>482</ymax>
    </bndbox>
  </object>
  <object>
    <name>1</name>
    <pose>Unspecified</pose>
    <truncated>0</truncated>
    <difficult>0</difficult>
    <bndbox>
      <xmin>479</xmin>
      <ymin>473</ymin>
      <xmax>520</xmax>
      <ymax>530</ymax>
    </bndbox>
  </object>
  <object>
    <name>1</name>
    <pose>Unspecified</pose>
    <truncated>0</truncated>
    <difficult>0</difficult>
    <bndbox>
      <xmin>886</xmin>
      <ymin>697</ymin>
      <xmax>920</xmax>
      <ymax>759</ymax>
    </bndbox>
  </object>
  <object>
    <name>1</name>
    <pose>Unspecified</pose>
    <truncated>0</truncated>
    <difficult>0</difficult>
    <bndbox>
      <xmin>289</xmin>
      <ymin>362</ymin>
      <xmax>334</xmax>
      <ymax>417</ymax>
    </bndbox>
  </object>
  <object>
    <name>1</name>
    <pose>Unspecified</pose>
    <truncated>0</truncated>
    <difficult>0</difficult>
    <bndbox>
      <xmin>296</xmin>
      <ymin>450</ymin>
      <xmax>334</xmax>
      <ymax>497</ymax>
    </bndbox>
  </object>
  <object>
    <name>1</name>
    <pose>Unspecified</pose>
    <truncated>0</truncated>
    <difficult>0</difficult>
    <bndbox>
      <xmin>296</xmin>
      <ymin>226</ymin>
      <xmax>330</xmax>
      <ymax>273</ymax>
    </bndbox>
  </object>
</annotation>
